setup.cfg
setup.py
my_latex_generator_nikitast1.egg-info/PKG-INFO
my_latex_generator_nikitast1.egg-info/SOURCES.txt
my_latex_generator_nikitast1.egg-info/dependency_links.txt
my_latex_generator_nikitast1.egg-info/top_level.txt
tsk_second/__init__.py
tsk_second/tsk2.2.py